{
	"name": "DELETESOURCE",
	"properties": {
		"linkedServiceName": {
			"referenceName": "PhysChem",
			"type": "LinkedServiceReference",
			"parameters": {
				"ServerName": "10.111.240.13"
			}
		},
		"annotations": [],
		"type": "SqlServerTable",
		"schema": [
			{
				"name": "KPI",
				"type": "varchar"
			},
			{
				"name": "Key",
				"type": "varchar"
			},
			{
				"name": "KeyName",
				"type": "varchar"
			},
			{
				"name": "ProcessGroup",
				"type": "varchar"
			},
			{
				"name": "ProcessGroupGlobal",
				"type": "varchar"
			},
			{
				"name": "Weight",
				"type": "int",
				"precision": 10
			}
		],
		"typeProperties": {
			"schema": "dbo",
			"table": "KPIKeys"
		}
	}
}