{
	"name": "FactUpdateTracker",
	"properties": {
		"linkedServiceName": {
			"referenceName": "supplydatastore_server",
			"type": "LinkedServiceReference"
		},
		"annotations": [],
		"type": "AzureSqlTable",
		"schema": [
			{
				"name": "pkiFactKPI",
				"type": "bigint",
				"precision": 19
			},
			{
				"name": "LastUpdated",
				"type": "datetime",
				"precision": 23,
				"scale": 3
			},
			{
				"name": "Value",
				"type": "float",
				"precision": 15
			},
			{
				"name": "SourceLine",
				"type": "bigint",
				"precision": 19
			},
			{
				"name": "DataSource",
				"type": "varchar"
			},
			{
				"name": "Updated",
				"type": "datetime",
				"precision": 23,
				"scale": 3
			}
		],
		"typeProperties": {
			"schema": "ODS",
			"table": "FactUpdates"
		}
	},
	"type": "Microsoft.DataFactory/factories/datasets"
}